docgen/.gitignore
docgen/__init__.py
docgen/config.toml.sample
docgen/config_manager.py
docgen/detector_config_loader.py
docgen/docgen.py
docgen/document_generator.py
docgen/generator_factory.py
docgen/hooks.toml
docgen/language_detector.py
docgen/archgen/__init__.py
docgen/archgen/cli.py
docgen/archgen/models.py
docgen/archgen/renderer.py
docgen/archgen/scanner.py
docgen/archgen/detectors/__init__.py
docgen/archgen/detectors/docker_detector.py
docgen/archgen/detectors/generic_detector.py
docgen/archgen/detectors/python_detector.py
docgen/archgen/generators/__init__.py
docgen/archgen/generators/mermaid_generator.py
docgen/benchmark/__init__.py
docgen/benchmark/comparator.py
docgen/benchmark/core.py
docgen/benchmark/models.py
docgen/benchmark/recorder.py
docgen/benchmark/reporter.py
docgen/benchmark/utils.py
docgen/cli/__init__.py
docgen/cli/parser.py
docgen/cli/runner.py
docgen/cli/commands/__init__.py
docgen/cli/commands/base.py
docgen/cli/commands/benchmark.py
docgen/cli/commands/build_index.py
docgen/cli/commands/generate.py
docgen/cli/commands/hooks.py
docgen/cli/commands/init.py
docgen/collectors/__init__.py
docgen/collectors/base_collector.py
docgen/collectors/coding_standards_collector.py
docgen/collectors/collector_utils.py
docgen/collectors/command_help_extractor.py
docgen/collectors/dependency_collector.py
docgen/collectors/language_info_collector.py
docgen/collectors/project_info_collector.py
docgen/collectors/structure_analyzer.py
docgen/config/__init__.py
docgen/config/config_accessor.py
docgen/detectors/__init__.py
docgen/detectors/base_detector.py
docgen/detectors/detector_patterns.py
docgen/detectors/plugin_registry.py
docgen/detectors/unified_detector.py
docgen/detectors/configs/go.toml
docgen/detectors/configs/javascript.toml
docgen/detectors/configs/python.toml
docgen/detectors/configs/typescript.toml
docgen/generators/__init__.py
docgen/generators/agents_generator.py
docgen/generators/api_generator.py
docgen/generators/base_generator.py
agents_docs_sync-0.2.1.dist-info/METADATA
agents_docs_sync-0.2.1.dist-info/WHEEL
agents_docs_sync-0.2.1.dist-info/entry_points.txt
agents_docs_sync-0.2.1.dist-info/licenses/LICENSE
agents_docs_sync-0.2.1.dist-info/RECORD
