Metadata-Version: 2.4
Name: agents-docs-sync
Version: 0.2.1
Summary: コミットするごとにテスト実行・ドキュメント生成・AGENTS.md の自動更新を行うパイプライン
Author-email: "塩ハム(d)" <shiohamu029@gmail.com>
License: MIT
License-File: LICENSE
Keywords: api-documentation,automation,ci-cd,documentation,github-actions,readme-generator
Classifier: Development Status :: 4 - Beta
Classifier: Intended Audience :: Developers
Classifier: License :: OSI Approved :: MIT License
Classifier: Programming Language :: Python :: 3
Classifier: Programming Language :: Python :: 3.12
Classifier: Programming Language :: Python :: 3.13
Classifier: Topic :: Software Development :: Documentation
Classifier: Topic :: Software Development :: Libraries :: Python Modules
Classifier: Topic :: Utilities
Requires-Python: >=3.12
Requires-Dist: anthropic>=0.74.1
Requires-Dist: hnswlib>=0.7.0
Requires-Dist: httpx>=0.28.1
Requires-Dist: jinja2>=3.1.0
Requires-Dist: openai>=2.8.1
Requires-Dist: outlines>=1.2.8
Requires-Dist: psutil>=5.9.0
Requires-Dist: pydantic>=2.0.0
Requires-Dist: pyyaml>=6.0.3
Requires-Dist: sentence-transformers>=2.2.0
Requires-Dist: torch>=2.0.0
